tnslack/__init__.py
tnslack/async_slack_app.py
tnslack/base_slack_app.py
tnslack/block_builder.py
tnslack/constants.py
tnslack/decorators.py
tnslack/exceptions.py
tnslack/slack_app.py
tnslack/utils.py
tn_slack_py_module-0.2.2.dist-info/METADATA
tn_slack_py_module-0.2.2.dist-info/WHEEL
tn_slack_py_module-0.2.2.dist-info/licenses/LICENSE
tn_slack_py_module-0.2.2.dist-info/RECORD
