Metadata-Version: 2.4
Name: tn-slack-py-module
Version: 0.2.2
Summary: An adaptation for slack
Project-URL: Homepage, https://github.com/thinknimble/tn-slack-py-module
Project-URL: Repository, https://github.com/thinknimble/tn-slack-py-module
Project-URL: Issues, https://github.com/thinknimble/tn-slack-py-module/issues
Author-email: Pari <pari@threeleafcoder.com>
License: MIT
License-File: LICENSE
Classifier: Development Status :: 3 - Alpha
Classifier: Intended Audience :: Developers
Classifier: License :: OSI Approved :: MIT License
Classifier: Programming Language :: Python :: 3
Classifier: Programming Language :: Python :: 3.10
Classifier: Programming Language :: Python :: 3.11
Classifier: Programming Language :: Python :: 3.12
Requires-Python: >=3.10
Requires-Dist: pydantic>=2.0.0
Requires-Dist: requests>=2.32.0
Requires-Dist: slack-sdk>=3.32.0
Requires-Dist: slackblocks>=1.1.0
Requires-Dist: typing-extensions>=4.0.0
